{
    "name": "porter-cnab",
    "version": "0.1.0",
    "description": "Install Draft Boot and MySQL on Azure",
    "invocationImages": [
        {
            "digest": "sha256:c17aa1dbfc876902c0f14b31fd95387945c0c3a4546f94abc79e99f92aed27c5",
            "imageType": "docker",
            "image": "jeremyrickard/draft-boot-mysql@sha256:c17aa1dbfc876902c0f14b31fd95387945c0c3a4546f94abc79e99f92aed27c5"
        }
    ],
    "images": null,
    "parameters": {},
    "credentials": {
        "CLIENT_ID": {
            "path": "",
            "env": "AZURE_CLIENT_ID"
        },
        "CLIENT_SECRET": {
            "path": "",
            "env": "AZURE_CLIENT_SECRET"
        },
        "SUBSCRIPTION_ID": {
            "path": "",
            "env": "AZURE_SUBSCRIPTION_ID"
        },
        "TENANT_ID": {
            "path": "",
            "env": "AZURE_TENANT_ID"
        },
        "kubeconfig": {
            "path": "/root/.kube/config",
            "env": ""
        }
    }
}
